[
  {
    "variation": "default-slice",
    "name": "Default slice",
    "slice_type": "home_services",
    "items": [
      {
        "title": [
          {
            "type": "paragraph",
            "text": "Aliquip ea irure reprehenderit Lorem ex aute anim consequat anim sunt proident. Minim non nulla enim eu commodo esse eu id mollit ad labore aliquip proident nisi. Ullamco nostrud non ut proident tempor ex pariatur veniam culpa eiusmod ex irure ipsum nulla.",
            "spans": []
          }
        ],
        "services": [
          {
            "type": "paragraph",
            "text": "Commodo nostrud irure do amet tempor sint cillum aliquip ex cupidatat nisi magna ut. Ullamco irure labore adipisicing pariatur aute nisi proident.",
            "spans": []
          }
        ]
      },
      {
        "title": [
          {
            "type": "paragraph",
            "text": "Lorem culpa do id non veniam eu ipsum enim minim.",
            "spans": []
          }
        ],
        "services": [
          {
            "type": "paragraph",
            "text": "Non est commodo dolor nostrud eu nulla pariatur laborum amet Lorem proident quis reprehenderit nisi laboris.",
            "spans": []
          }
        ]
      },
      {
        "title": [
          {
            "type": "paragraph",
            "text": "Amet occaecat amet fugiat dolore.",
            "spans": []
          }
        ],
        "services": [
          {
            "type": "paragraph",
            "text": "Aliqua esse voluptate in Lorem sit nostrud nostrud. Exercitation veniam nulla excepteur nisi duis do nisi fugiat minim incididunt adipisicing nulla.",
            "spans": []
          }
        ]
      }
    ],
    "primary": {
      "title": [
        {
          "type": "heading1",
          "text": "Reintermediate extensible deliverables",
          "spans": []
        }
      ],
      "description": [
        {
          "type": "paragraph",
          "text": "Incididunt minim qui sit Lorem labore reprehenderit eu irure eu qui aute veniam reprehenderit.",
          "spans": []
        }
      ],
      "image": {
        "dimensions": {
          "width": 900,
          "height": 500
        },
        "alt": "Placeholder image",
        "copyright": null,
        "url": "https://images.unsplash.com/photo-1593642633279-1796119d5482?w=900&h=500&fit=crop"
      }
    }
  }
]